nltkjsonnlp/__init__.py
nltkjsonnlp/server.py
tests/__init__.py
tests/mocks.py
tests/test_nltkjsonnlp.py
nltkjsonnlp-0.0.5.dist-info/LICENSE
nltkjsonnlp-0.0.5.dist-info/METADATA
nltkjsonnlp-0.0.5.dist-info/WHEEL
nltkjsonnlp-0.0.5.dist-info/top_level.txt
nltkjsonnlp-0.0.5.dist-info/RECORD
