Metadata-Version: 2.1
Name: nltkjsonnlp
Version: 0.0.5
Summary: The Python NLTK JSON-NLP package
Home-page: https://github.com/dcavar/NLTK-JSON-NLP
Author: Damir Cavar, Oren Baldinger, Maanvitha Gongalla, Anurag Kumar, Murali Kammili, Boli Fang
Author-email: damir@cavar.me
License: UNKNOWN
Platform: UNKNOWN
Classifier: Programming Language :: Python :: 3
Classifier: License :: OSI Approved :: Apache Software License
Classifier: Operating System :: OS Independent
Requires-Dist: nltk (>=3.4)
Requires-Dist: pyjsonnlp (>=0.2.9)
